{
  "positions": [
    "백엔드/서버 개발자",
    "프론트엔드 개발자",
    "웹 풀스택",
    "앱 개발자",
    "안드로이드 개발자",
    "아이폰 개발자",
    "인공지능(AI)",
    "시스템/네트워크",
    "시스템 소프트웨어",
    "인터넷 보안",
    "블록체인",
    "응용 프로그래밍",
    "게임 서버",
    "게임 프로그래밍",
    "모바일 게임",
    "데이터 엔지니어링"
  ],
  "companies": [
    "Nexon",
    "WATCHA",
    "플랫팜",
    "백패커",
    "피유엠피",
    "EA KOREA",
    "CODE 42",
    "와이즈케어",
    "웨이버스",
    "유니콘소프트",
    "스파이스웨어",
    "카카오엔터프라이즈",
    "잼팟",
    "애니포인트미디어",
    "비프로컴퍼니",
    "직방"
  ],
  "address": [
    "서울 강남구 강남대로 408, (역삼동) 11층",
    "마포 잔다리로3길 7, 현제빌딩 3층",
    "서울시 강남구 도곡동 514-1 튼튼영어빌딩 10층",
    "서울시 강남구 도곡동 514-1 튼튼영어빌딩 10층",
    "서울 동대문구 회기로 117-3 산업지원동 403호",
    "서울시 서초구 서초중앙로 14 하이트진로 빌딩 16F",
    "서울 성동구 상원12길 1, (성수동1가) 3층",
    "서울 구로구 디지털로32가길 16, (구로동) 1301",
    "경기도 성남시 분당구 운중로 249, 더제이에스타워 5층",
    "경기도 성남시 분당구 판교역로 235, N동 3층",
    "경기 성남시 분당구 느티로 16, (정자동)",
    "경기 성남시 분당구 대왕판교로 670, (삼평동) 유스페이스2 B동 509호",
    "경기 성남시 분당구 판교로 323, 5층(삼평동, 투썬벤처포럼빌딩)",
    "경기도 성남시 분당구 분당내곡로 117(백현동, 크래프톤타워)",
    "경기 성남시 분당구 분당내곡로 117, (백현동)",
    "서울 광진구 능동로 243-1, (군자동) 2층"
  ],
  "career": ["신입", "주니어", "시니어", "리드", "경력 무관"],
  "skills": [
    "JavaScript",
    "React",
    "React-Native",
    "Vue-js",
    "JQuery",
    "HTML5",
    "CSS",
    "SASS",
    "ES6",
    "Node.js",
    "JAVA",
    "Spring",
    "SpringBoot",
    "JSP",
    "AWS",
    "REST API",
    "PHP",
    "Python",
    "Django",
    "Flask",
    "express",
    "Angular",
    "GraphQL",
    "MySQL",
    "Git",
    "Web FullStack",
    "C#",
    "ASP",
    ".Net Core",
    "Docker",
    "docker-compose",
    "kubernetes",
    "Go",
    "Swift",
    "Objective-C",
    "C",
    "C++",
    "Winform",
    "MFC",
    "Data Engineer",
    "SQL",
    "Tensorflow",
    "Machne Learning",
    "Data mining",
    "Deep Learning",
    "QA",
    "Apache2",
    "Nginx",
    "TypeScript",
    "PostgresSQL",
    "Unity3D",
    "WebGL",
    "OpenGL",
    "DirectX",
    "DirectX",
    "MobX",
    "MyBatis",
    ".NET Visual Basic",
    "Unreal Engine",
    "Cocos2d",
    "MongoDB",
    "NoSQL",
    "Linux"
  ],
  "signingBonus": [0, 300000, 500000, 1000000]
}
